safetensors_layer_grabber.py
safetensors_layer_grabber-0.1.0a2.dist-info/licenses/LICENSE
safetensors_layer_grabber-0.1.0a2.dist-info/METADATA
safetensors_layer_grabber-0.1.0a2.dist-info/WHEEL
safetensors_layer_grabber-0.1.0a2.dist-info/top_level.txt
safetensors_layer_grabber-0.1.0a2.dist-info/RECORD
