Metadata-Version: 2.4
Name: safetensors-layer-grabber
Version: 0.1.0a2
Summary: Extracts all weights corresponding to a specific layer or block from large models saved in safetensors format, and exports them as a PyTorch-compatible state dict.
Author-email: Jifeng Wu <jifengwu2k@gmail.com>
License-Expression: MIT
Project-URL: Homepage, https://github.com/jifengwu2k/safetensors-layer-grabber
Project-URL: Bug Tracker, https://github.com/jifengwu2k/safetensors-layer-grabber/issues
Classifier: Programming Language :: Python :: 2
Classifier: Programming Language :: Python :: 3
Classifier: Operating System :: OS Independent
Requires-Python: >=2
License-File: LICENSE
Requires-Dist: torch
Requires-Dist: safetensors
Dynamic: license-file
